foursquare/map_sdk/__init__.py
foursquare/map_sdk/_frontend.py
foursquare/map_sdk/_poll.py
foursquare/map_sdk/_version.py
foursquare/map_sdk/colab.py
foursquare/map_sdk/environment.py
foursquare/map_sdk/errors.py
foursquare/map_sdk/poll.py
foursquare/map_sdk/types.py
foursquare/map_sdk/_poll_v56/__init__.py
foursquare/map_sdk/_poll_v56/_async_thread.py
foursquare/map_sdk/_poll_v56/_poll.py
foursquare/map_sdk/_poll_v56/_version.py
foursquare/map_sdk/api/__init__.py
foursquare/map_sdk/api/annotation_api.py
foursquare/map_sdk/api/base.py
foursquare/map_sdk/api/color.py
foursquare/map_sdk/api/columns.py
foursquare/map_sdk/api/create_map.py
foursquare/map_sdk/api/dataset_api.py
foursquare/map_sdk/api/effect_api.py
foursquare/map_sdk/api/enums.py
foursquare/map_sdk/api/event_api.py
foursquare/map_sdk/api/filter_api.py
foursquare/map_sdk/api/layer_api.py
foursquare/map_sdk/api/map_api.py
foursquare/map_sdk/api/text_label.py
foursquare/map_sdk/api/tooltip_api.py
foursquare/map_sdk/api/layer/__init__.py
foursquare/map_sdk/api/layer/arc.py
foursquare/map_sdk/api/layer/cluster.py
foursquare/map_sdk/api/layer/flow.py
foursquare/map_sdk/api/layer/grid.py
foursquare/map_sdk/api/layer/h3.py
foursquare/map_sdk/api/layer/heatmap.py
foursquare/map_sdk/api/layer/hexbin.py
foursquare/map_sdk/api/layer/hextile.py
foursquare/map_sdk/api/layer/icon.py
foursquare/map_sdk/api/layer/line.py
foursquare/map_sdk/api/layer/point.py
foursquare/map_sdk/api/layer/polygon.py
foursquare/map_sdk/api/layer/raster.py
foursquare/map_sdk/api/layer/s2.py
foursquare/map_sdk/api/layer/threed.py
foursquare/map_sdk/api/layer/threedtile.py
foursquare/map_sdk/api/layer/trip.py
foursquare/map_sdk/api/layer/vector.py
foursquare/map_sdk/api/layer/wms.py
foursquare/map_sdk/generated/Animation.py
foursquare/map_sdk/generated/Annotation.py
foursquare/map_sdk/generated/Chart.py
foursquare/map_sdk/generated/CrossFilter.py
foursquare/map_sdk/generated/CustomMapState.py
foursquare/map_sdk/generated/Effect.py
foursquare.map_sdk-3.1.0.dist-info/LICENSE.txt
foursquare.map_sdk-3.1.0.dist-info/METADATA
foursquare.map_sdk-3.1.0.dist-info/WHEEL
foursquare.map_sdk-3.1.0.dist-info/top_level.txt
foursquare.map_sdk-3.1.0.dist-info/RECORD
